odoo/addons/l10n_fi_banks/README.rst
odoo/addons/l10n_fi_banks/__init__.py
odoo/addons/l10n_fi_banks/__manifest__.py
odoo/addons/l10n_fi_banks/data/res_bank.xml
odoo/addons/l10n_fi_banks/i18n/fi.po
odoo/addons/l10n_fi_banks/i18n/l10n_fi_banks.pot
odoo/addons/l10n_fi_banks/static/description/icon.png
odoo13_addon_l10n_fi_banks-13.0.1.0.0.dist-info/METADATA
odoo13_addon_l10n_fi_banks-13.0.1.0.0.dist-info/WHEEL
odoo13_addon_l10n_fi_banks-13.0.1.0.0.dist-info/top_level.txt
odoo13_addon_l10n_fi_banks-13.0.1.0.0.dist-info/RECORD
